  <varray name="forces" >
   <v>       0.00003464      -0.00000291      -0.18999403 </v>
   <v>      -0.00002538       0.00002466      -0.18991950 </v>
   <v>      -0.00000796       0.00002679      -0.18980925 </v>
   <v>       0.00004809       0.00001335      -0.18995573 </v>
   <v>       0.00033181      -0.00026530      -0.18654235 </v>
   <v>       0.00029605      -0.00025813      -0.18649344 </v>
   <v>       0.00036561      -0.00018584      -0.18635050 </v>
   <v>       0.00039915      -0.00021453      -0.18642119 </v>
   <v>      -0.00012393       0.00044546      -0.18663178 </v>
   <v>      -0.00004544       0.00037641      -0.18653238 </v>
   <v>       0.00004010       0.00044192      -0.18641331 </v>
   <v>       0.00001824       0.00043390      -0.18639269 </v>
   <v>      -0.00037372      -0.00021937      -0.18643427 </v>
   <v>      -0.00037332      -0.00021834      -0.18641197 </v>
   <v>      -0.00032889      -0.00019627      -0.18638955 </v>
   <v>      -0.00033116      -0.00018953      -0.18641383 </v>
   <v>      -0.00010623      -0.00015026       0.00418571 </v>
   <v>      -0.00011344      -0.00011937       0.00442631 </v>
   <v>       0.00004687       0.00000446       0.00461837 </v>
   <v>       0.00005169       0.00002338       0.00452214 </v>
   <v>      -0.00781259       0.00464792       0.00345434 </v>
   <v>      -0.00790509       0.00465724       0.00335211 </v>
   <v>      -0.00787209       0.00461277       0.00328726 </v>
   <v>      -0.00799423       0.00463037       0.00338085 </v>
   <v>       0.00011544      -0.00920458       0.00334982 </v>
   <v>       0.00003555      -0.00910542       0.00341250 </v>
   <v>      -0.00004700      -0.00915254       0.00349291 </v>
   <v>       0.00003551      -0.00927036       0.00328717 </v>
   <v>       0.00759617       0.00472177       0.00254225 </v>
   <v>       0.00782944       0.00451095       0.00314075 </v>
   <v>       0.00779768       0.00457077       0.00381294 </v>
   <v>       0.00806048       0.00462111       0.00333471 </v>
   <v>       0.00052502       0.00016763       0.00030119 </v>
   <v>       0.00006794       0.00018070       0.00022081 </v>
   <v>      -0.00085370      -0.00048342       0.00199934 </v>
   <v>       0.00009259      -0.00003105      -0.00012911 </v>
   <v>      -0.00032574      -0.00036507      -0.00039935 </v>
   <v>      -0.00022827      -0.00045328      -0.00007758 </v>
   <v>       0.00015567      -0.00000596       0.00028133 </v>
   <v>      -0.00003251       0.00033004       0.00030288 </v>
   <v>      -0.00171524       0.00062599      -0.00276525 </v>
   <v>      -0.00024513      -0.00007971       0.00007629 </v>
   <v>       0.00019387      -0.00014589       0.00047562 </v>
   <v>       0.00011532       0.00002649       0.00019766 </v>
   <v>       0.00024605       0.00012964       0.00035407 </v>
   <v>       0.00011477       0.00008944       0.00028918 </v>
   <v>       0.00002295       0.00006031       0.00046767 </v>
   <v>       0.00010127      -0.00002920       0.00012080 </v>
   <v>      -0.00055445      -0.00117702      -0.00122056 </v>
   <v>      -0.00050064      -0.00017241       0.00022697 </v>
   <v>       0.00008304       0.00017956       0.00052082 </v>
   <v>       0.00017946      -0.00003436       0.00045791 </v>
   <v>       0.00159243       0.00071086       0.00169442 </v>
   <v>       0.00025772       0.00004722       0.00014352 </v>
   <v>       0.00072272      -0.00058040       0.00250963 </v>
   <v>       0.00017563      -0.00006288      -0.00024411 </v>
   <v>       0.00035282       0.00058430       0.00091519 </v>
   <v>       0.00033503       0.00022263       0.00009017 </v>
   <v>       0.00020485      -0.00008180      -0.00002881 </v>
   <v>      -0.00019612       0.00097065       0.00098877 </v>
   <v>      -0.00758739       0.00048982      -0.01532012 </v>
   <v>      -0.00022527      -0.00035844      -0.00073196 </v>
   <v>       0.00022280      -0.00003553       0.00049963 </v>
   <v>      -0.00014660       0.00015895       0.00038965 </v>
   <v>       0.00036217       0.00042009       0.00003193 </v>
   <v>      -0.00114034       0.00015987      -0.00020639 </v>
   <v>      -0.01360793      -0.02740758      -0.00018081 </v>
   <v>      -0.00087029      -0.00146650       0.00030928 </v>
   <v>      -0.00105562      -0.00173645      -0.00028358 </v>
   <v>       0.00025613       0.00020471       0.00004406 </v>
   <v>      -0.11758677       0.02746261      -0.00214220 </v>
   <v>      -0.00243903      -0.00357908       0.00056597 </v>
   <v>       0.00258579       0.00244701       0.00010750 </v>
   <v>       0.00127073       0.00034764       0.00000435 </v>
   <v>       0.00199631       0.00226223      -0.00007102 </v>
   <v>       0.00021146      -0.00057359       0.00003036 </v>
   <v>       0.00002485       0.00000094      -0.04726576 </v>
   <v>       0.00002355       0.00002019      -0.04734512 </v>
   <v>      -0.00004977      -0.00004103      -0.04753062 </v>
   <v>      -0.00003970      -0.00001174      -0.04728242 </v>
   <v>       0.00080742       0.00046036      -0.05490482 </v>
   <v>       0.00079245       0.00048414      -0.05494753 </v>
   <v>       0.00073085       0.00044304      -0.05496131 </v>
   <v>       0.00076227       0.00043176      -0.05491680 </v>
   <v>      -0.00004449      -0.00087112      -0.05456718 </v>
   <v>       0.00002049      -0.00092024      -0.05475076 </v>
   <v>       0.00002791      -0.00090552      -0.05490684 </v>
   <v>      -0.00001566      -0.00089639      -0.05495687 </v>
   <v>      -0.00077927       0.00046293      -0.05476482 </v>
   <v>      -0.00076466       0.00045264      -0.05480184 </v>
   <v>      -0.00077470       0.00045266      -0.05499888 </v>
   <v>      -0.00079306       0.00046207      -0.05491530 </v>
   <v>       0.00008041      -0.00002085      -0.01262194 </v>
   <v>       0.00001823       0.00010838      -0.01296482 </v>
   <v>      -0.00004998       0.00001952      -0.01317478 </v>
   <v>       0.00002140      -0.00000455      -0.01302996 </v>
   <v>       0.04317326       0.02516330       0.02428937 </v>
   <v>       0.04337750       0.02496658       0.02319011 </v>
   <v>       0.04330357       0.02499937       0.02200383 </v>
   <v>       0.04330244       0.02504089       0.02285062 </v>
   <v>      -0.00011354      -0.05008504       0.02278432 </v>
   <v>      -0.00004536      -0.05014077       0.02275657 </v>
   <v>       0.00006643      -0.05001297       0.02259898 </v>
   <v>       0.00002488      -0.04999491       0.02284955 </v>
   <v>      -0.04352017       0.02495936       0.02262041 </v>
   <v>      -0.04340151       0.02496746       0.02280883 </v>
   <v>      -0.04322485       0.02500696       0.02283087 </v>
   <v>      -0.04333115       0.02508668       0.02274581 </v>
   <v>      -0.00034276      -0.00015730      -0.00067128 </v>
   <v>      -0.00008707      -0.00011142      -0.00041625 </v>
   <v>      -0.00011404      -0.00056321      -0.00472624 </v>
   <v>      -0.00003445       0.00008777       0.00009633 </v>
   <v>      -0.00019387      -0.00009822      -0.00038329 </v>
   <v>      -0.00011880      -0.00006714      -0.00018190 </v>
   <v>       0.00001036       0.00013879      -0.00041526 </v>
   <v>       0.00011105       0.00004462      -0.00001891 </v>
   <v>      -0.00074480       0.00089168       0.00724402 </v>
   <v>       0.00013880       0.00005272       0.00001443 </v>
   <v>      -0.00008166      -0.00010956      -0.00057402 </v>
   <v>      -0.00002417       0.00001015      -0.00006529 </v>
   <v>       0.00078427      -0.00011865       0.00108386 </v>
   <v>       0.00004689       0.00013729       0.00038993 </v>
   <v>      -0.00007515       0.00004260      -0.00016271 </v>
   <v>       0.00002425      -0.00014470      -0.00010875 </v>
   <v>      -0.00217696       0.00833428       0.00038545 </v>
   <v>      -0.00009431      -0.00097761       0.00012682 </v>
   <v>      -0.00050194      -0.00037717      -0.00019069 </v>
   <v>      -0.00015569       0.00010880      -0.00009370 </v>
   <v>       0.14373260      -0.00908819       0.01127107 </v>
   <v>       0.00068080       0.00211564       0.00003223 </v>
   <v>      -0.00120181       0.00066821      -0.00002553 </v>
   <v>       0.00018508      -0.00012400      -0.00009425 </v>
   <v>       0.00040087      -0.00009076      -0.00017409 </v>
   <v>      -0.00071258      -0.00065344      -0.00010522 </v>
   <v>       0.00023025      -0.00012301       0.00009115 </v>
   <v>      -0.00077408      -0.00380443      -0.00028542 </v>
   <v>       0.00165772       0.00081384      -0.00059471 </v>
   <v>      -0.00032583      -0.00020135      -0.00016441 </v>
   <v>      -0.00227116       0.00295988      -0.00032266 </v>
   <v>      -0.00033134       0.00087875       0.00013723 </v>
   <v>       0.00000468       0.00049779       0.22305702 </v>
   <v>       0.00001192       0.00049266       0.22302918 </v>
   <v>      -0.00000392       0.00048057       0.22301033 </v>
   <v>      -0.00001011       0.00048984       0.22304536 </v>
   <v>       0.00043573      -0.00024536       0.22305457 </v>
   <v>       0.00042823      -0.00024916       0.22304635 </v>
   <v>       0.00041858      -0.00025219       0.22303180 </v>
   <v>       0.00041461      -0.00025712       0.22303583 </v>
   <v>      -0.00042384      -0.00023874       0.22310299 </v>
   <v>      -0.00039807      -0.00024576       0.22311393 </v>
   <v>      -0.00043054      -0.00025147       0.22301824 </v>
   <v>      -0.00043758      -0.00024982       0.22305030 </v>
   <v>       0.00000949       0.00001143       0.22249329 </v>
   <v>       0.00001163       0.00001053       0.22250575 </v>
   <v>      -0.00000370      -0.00000205       0.22244423 </v>
   <v>      -0.00000621       0.00000023       0.22243642 </v>
   <v>      -0.00002249      -0.00001498      -0.00018292 </v>
   <v>      -0.00001310      -0.00001658      -0.00018226 </v>
   <v>       0.00001235       0.00000051      -0.00018587 </v>
   <v>       0.00000079       0.00000809      -0.00018715 </v>
   <v>      -0.00033941       0.00020509      -0.00023818 </v>
   <v>      -0.00033831       0.00021519      -0.00023875 </v>
   <v>      -0.00035702       0.00020676      -0.00024049 </v>
   <v>      -0.00033500       0.00020161      -0.00023987 </v>
   <v>       0.00033658       0.00018776      -0.00023566 </v>
   <v>       0.00027754       0.00020005      -0.00023420 </v>
   <v>       0.00035299       0.00021581      -0.00024075 </v>
   <v>       0.00036947       0.00020880      -0.00023879 </v>
   <v>       0.00000947      -0.00040415      -0.00023811 </v>
   <v>       0.00000307      -0.00039242      -0.00024036 </v>
   <v>      -0.00000507      -0.00039560      -0.00024168 </v>
   <v>       0.00000122      -0.00040555      -0.00023985 </v>
