  <varray name="forces" >
   <v>      -0.00041026       0.00022325       0.19983386 </v>
   <v>       0.00056562       0.00034900       0.19968492 </v>
   <v>       0.00025534      -0.00026960       0.19994609 </v>
   <v>       0.00024582      -0.00016774       0.19984825 </v>
   <v>      -0.00060433       0.00112621       0.20031424 </v>
   <v>       0.00070258      -0.00072060       0.19872868 </v>
   <v>       0.00012946      -0.00043269       0.19985272 </v>
   <v>       0.00000239       0.00016984       0.19980839 </v>
   <v>      -0.00099875      -0.00019159       0.20061701 </v>
   <v>       0.00098333       0.00058533      -0.15054076 </v>
   <v>      -0.00019121       0.00008599      -0.14991247 </v>
   <v>      -0.00002069      -0.00029141      -0.14981786 </v>
   <v>       0.00047223      -0.00010709      -0.15000150 </v>
   <v>       0.00012809      -0.00104201      -0.15044469 </v>
   <v>      -0.00011545       0.00139521      -0.14909315 </v>
   <v>      -0.00141424      -0.00045825      -0.14947941 </v>
   <v>       0.00009932       0.00005871      -0.14992308 </v>
   <v>       0.00017675      -0.00027543      -0.14985410 </v>
   <v>      -0.00463804      -0.00227892      -0.05949222 </v>
   <v>       0.00061988      -0.00028280      -0.05741649 </v>
   <v>       0.00014210       0.00031835      -0.05790923 </v>
   <v>       0.00306424      -0.00207311      -0.06199034 </v>
   <v>      -0.00060775       0.00501559      -0.05969196 </v>
   <v>       0.00084780      -0.00109970      -0.06229041 </v>
   <v>       0.00156493      -0.00040787      -0.06080305 </v>
   <v>      -0.00001304      -0.00009721      -0.05777819 </v>
   <v>      -0.00099011       0.00079566      -0.05865320 </v>
   <v>       0.00781288      -0.00437781      -0.16026312 </v>
   <v>      -0.00111848       0.01009056       0.00572419 </v>
   <v>       0.00079253      -0.00136678       0.00755510 </v>
   <v>       0.00044970       0.00050709       0.00677497 </v>
   <v>       0.00119043      -0.00023921       0.00780400 </v>
   <v>      -0.00161344      -0.00017448       0.00660785 </v>
   <v>      -0.00824107      -0.00347929       0.00510544 </v>
   <v>      -0.00006985       0.00015057       0.00683639 </v>
   <v>       0.00083476      -0.00102656       0.00797362 </v>
   <v>       0.04207420      -0.02503477       0.23943940 </v>
   <v>      -0.00413760       0.04725285      -0.03410353 </v>
   <v>      -0.00195916      -0.00051152      -0.00084550 </v>
   <v>       0.00099477       0.00114109       0.00166880 </v>
   <v>       0.00433980      -0.00088309       0.00314985 </v>
   <v>      -0.00111008       0.00242082      -0.00308634 </v>
   <v>      -0.04385113      -0.02108905      -0.03185831 </v>
   <v>      -0.00023513       0.00022696       0.00096456 </v>
   <v>       0.00308473      -0.00260455       0.00286555 </v>
   <v>       0.03787336      -0.01563734       0.07040543 </v>
   <v>      -0.00064817      -0.00187976       0.00031359 </v>
   <v>       0.00159977       0.03878477      -0.03175083 </v>
   <v>      -0.03883238      -0.01799197      -0.03124984 </v>
   <v>       0.00279826      -0.00258671       0.00092231 </v>
   <v>      -0.00055613      -0.00066353      -0.00061620 </v>
   <v>       0.00169758       0.00202046      -0.00012315 </v>
   <v>      -0.00215660       0.00170185      -0.00137553 </v>
   <v>      -0.00099718      -0.00479551       0.00006306 </v>
   <v>       0.00765245       0.03418597       0.06706937 </v>
   <v>       0.00060003       0.00029848       0.00918992 </v>
   <v>       0.03633534      -0.00913012      -0.01521425 </v>
   <v>      -0.00862816      -0.00727860       0.00453553 </v>
   <v>      -0.00076113       0.00099864       0.00670426 </v>
   <v>      -0.00019102       0.00310871       0.01118248 </v>
   <v>       0.00093286      -0.00390427       0.00764718 </v>
   <v>       0.00009953       0.00086733       0.00796671 </v>
   <v>      -0.03619831      -0.01701954      -0.01199592 </v>
   <v>      -0.05118659      -0.02560271       0.09551372 </v>
   <v>       0.00585301      -0.00208634      -0.00039375 </v>
   <v>       0.00082394       0.00014625       0.00433178 </v>
   <v>       0.05589158      -0.03359400      -0.01894890 </v>
   <v>      -0.00491297      -0.12269606       0.04234591 </v>
   <v>      -0.00078748       0.00072548       0.00411317 </v>
   <v>      -0.00241846      -0.00052025       0.00411476 </v>
   <v>      -0.00099390      -0.00023667       0.00409366 </v>
   <v>      -0.00005878      -0.00152754       0.00419581 </v>
   <v>      -0.00663285      -0.01450638      -0.00545080 </v>
   <v>      -0.00086941       0.00034803       0.00011618 </v>
   <v>      -0.00048256       0.00050018      -0.00040379 </v>
   <v>      -0.00045564      -0.00044102       0.00008899 </v>
   <v>      -0.00031700       0.00005764      -0.00030849 </v>
   <v>       0.00003611       0.00013812       0.00017828 </v>
   <v>       0.00707933      -0.00388740      -0.00441770 </v>
   <v>       0.00119759      -0.00017968      -0.00082526 </v>
   <v>       0.00046733       0.00912226      -0.00531942 </v>
   <v>       0.00104884      -0.00078721      -0.00094240 </v>
   <v>      -0.00058903       0.00012028      -0.00031186 </v>
   <v>      -0.00026637      -0.00232326       0.00042024 </v>
   <v>      -0.00212558      -0.00110158      -0.00086157 </v>
   <v>       0.00003820      -0.00012215      -0.00019852 </v>
   <v>      -0.00008539       0.00006754      -0.00029547 </v>
   <v>       0.00104657      -0.00073301      -0.00049180 </v>
   <v>       0.00051998       0.00136659      -0.00071119 </v>
   <v>       0.00032231       0.00015966      -0.00048992 </v>
   <v>       0.00183536       0.03801369       0.02882239 </v>
   <v>       0.03406186      -0.01699023      -0.03014468 </v>
   <v>       0.00005619      -0.00107102      -0.01173355 </v>
   <v>      -0.00127187      -0.00318150      -0.01640717 </v>
   <v>      -0.03449382      -0.01527643      -0.01493657 </v>
   <v>       0.00011098      -0.00031002      -0.00879805 </v>
   <v>      -0.00047732      -0.00216707      -0.01147731 </v>
   <v>       0.00050897       0.00290058      -0.01076185 </v>
   <v>      -0.00012529      -0.00092573      -0.00717889 </v>
   <v>      -0.05095758       0.18233355      -0.03147163 </v>
   <v>       0.00853556      -0.00544803      -0.00781146 </v>
   <v>       0.00487031      -0.00603729      -0.00542392 </v>
   <v>       0.00180037       0.00263119      -0.00063149 </v>
   <v>      -0.00767861      -0.00384412      -0.00930004 </v>
   <v>       0.00029202      -0.00149437      -0.00465152 </v>
   <v>       0.04684012      -0.02469678      -0.03065033 </v>
   <v>      -0.00081561       0.00044844      -0.00686836 </v>
   <v>      -0.00511950       0.04816486      -0.03687802 </v>
   <v>      -0.00209726       0.00103288      -0.00097562 </v>
   <v>       0.00129294      -0.00051557       0.00158174 </v>
   <v>       0.00116715       0.00306138       0.00726113 </v>
   <v>       0.00477132       0.00122665      -0.00200621 </v>
   <v>      -0.00019250       0.00011760       0.00114670 </v>
   <v>       0.00033071      -0.00018933       0.00139843 </v>
   <v>      -0.00268832       0.00113123       0.00017753 </v>
   <v>      -0.00112158      -0.00371676       0.00027959 </v>
   <v>      -0.00152013      -0.00065323       0.00171280 </v>
   <v>       0.00078264      -0.00077921       0.00125285 </v>
   <v>      -0.00007436       0.00105510       0.00075269 </v>
   <v>       0.00067919       0.00149927       0.00207023 </v>
   <v>      -0.00043896      -0.00115711       0.00117908 </v>
   <v>      -0.00015561       0.00086824       0.00131446 </v>
   <v>       0.00004713       0.00009113       0.00116824 </v>
   <v>      -0.00031479      -0.00064202       0.00103890 </v>
   <v>       0.00025930       0.00037804      -0.00019354 </v>
   <v>      -0.00069729       0.00010342       0.00111575 </v>
   <v>      -0.00019836       0.00023909       0.00008144 </v>
   <v>       0.00016209      -0.00024399      -0.00014212 </v>
   <v>      -0.00018867      -0.00059284       0.00037786 </v>
   <v>       0.00010836       0.00032129       0.00009785 </v>
   <v>       0.00002631      -0.00018904       0.00002812 </v>
   <v>      -0.00004360      -0.00000678       0.00008789 </v>
   <v>       0.00009056       0.00016688       0.00001349 </v>
   <v>      -0.00018780      -0.00004194      -0.00046240 </v>
   <v>       0.00023240      -0.00001122      -0.00001140 </v>
   <v>       0.00016446      -0.00009877      -0.00028942 </v>
   <v>      -0.00019482      -0.00017441      -0.00036007 </v>
   <v>      -0.00010701       0.00018059      -0.00027162 </v>
   <v>      -0.00015646       0.00002914      -0.00028015 </v>
   <v>       0.00021947      -0.00072183      -0.00023475 </v>
   <v>      -0.00048873       0.00044298      -0.00042881 </v>
   <v>      -0.00000816       0.00013046      -0.00032713 </v>
   <v>      -0.00002409      -0.00005711      -0.00033439 </v>
   <v>       0.00059563       0.00025055      -0.00018748 </v>
