  <varray name="forces" >
   <v>       0.00002104      -0.00000199       0.10098014 </v>
   <v>       0.00000747      -0.00004684       0.10101193 </v>
   <v>      -0.00007186      -0.00000062       0.10098284 </v>
   <v>       0.00000687       0.00004413       0.10095251 </v>
   <v>      -0.00890629       0.00517566       0.06874554 </v>
   <v>      -0.00894414       0.00515544       0.06875857 </v>
   <v>      -0.00890181       0.00519127       0.06879501 </v>
   <v>      -0.00888839       0.00506770       0.06868115 </v>
   <v>       0.00002176      -0.01027186       0.06874226 </v>
   <v>       0.00009028      -0.01029419       0.06875463 </v>
   <v>       0.00002256      -0.01031597       0.06876906 </v>
   <v>      -0.00010946      -0.01029355       0.06875376 </v>
   <v>       0.00892898       0.00510269       0.06871471 </v>
   <v>       0.00888750       0.00513880       0.06875118 </v>
   <v>       0.00892408       0.00511817       0.06876500 </v>
   <v>       0.00894202       0.00522507       0.06882763 </v>
   <v>      -0.00002156       0.00001231      -0.05647692 </v>
   <v>      -0.00004521      -0.00000034      -0.05642691 </v>
   <v>      -0.00002180      -0.00001486      -0.05637635 </v>
   <v>       0.00011096      -0.00000171      -0.05642753 </v>
   <v>       0.00489774      -0.00282672      -0.07947712 </v>
   <v>       0.00497516      -0.00292463      -0.07950712 </v>
   <v>       0.00503246      -0.00289422      -0.07956699 </v>
   <v>       0.00504195      -0.00291998      -0.07960538 </v>
   <v>       0.00000349       0.00575171      -0.07953008 </v>
   <v>       0.00000248       0.00572948      -0.07949191 </v>
   <v>      -0.00008916       0.00574957      -0.07953155 </v>
   <v>       0.00000278       0.00577253      -0.07956847 </v>
   <v>      -0.00506682      -0.00292837      -0.07958503 </v>
   <v>      -0.00492434      -0.00283321      -0.07945708 </v>
   <v>      -0.00493319      -0.00286182      -0.07949527 </v>
   <v>      -0.00498819      -0.00282900      -0.07955463 </v>
   <v>       0.00012528       0.00005306      -0.00023548 </v>
   <v>       0.00001095      -0.00001129      -0.00025075 </v>
   <v>      -0.00006320      -0.00002492      -0.00025526 </v>
   <v>      -0.00003214      -0.00002940      -0.00021381 </v>
   <v>       0.00000667      -0.00007509      -0.00024642 </v>
   <v>       0.00003742      -0.00000262      -0.00025136 </v>
   <v>       0.00000716       0.00006679      -0.00025888 </v>
   <v>       0.00002144      -0.00000275      -0.00025033 </v>
   <v>      -0.00006749       0.00002961      -0.00025019 </v>
   <v>       0.00000626       0.00001566      -0.00025812 </v>
   <v>       0.00012289      -0.00004705      -0.00027736 </v>
   <v>      -0.00003705       0.00003530      -0.00029503 </v>
   <v>       0.00002533       0.00000229      -0.00011524 </v>
   <v>       0.00000787       0.00000810       0.00000411 </v>
   <v>       0.00001847       0.00000186      -0.00011333 </v>
   <v>       0.00000532      -0.00000557      -0.00023292 </v>
   <v>       0.00010043       0.00000201      -0.00048077 </v>
   <v>      -0.00004486      -0.00008364      -0.00062744 </v>
   <v>      -0.00019297       0.00000186      -0.00048930 </v>
   <v>      -0.00004503       0.00008737      -0.00034785 </v>
   <v>      -0.00009681       0.00006720      -0.00033332 </v>
   <v>      -0.00006442       0.00000384      -0.00036488 </v>
   <v>       0.00005219      -0.00000703      -0.00053852 </v>
   <v>       0.00010758      -0.00002708      -0.00039632 </v>
   <v>      -0.00002157      -0.00005244      -0.00034385 </v>
   <v>       0.00003942       0.00000755      -0.00037510 </v>
   <v>      -0.00001759       0.00006860      -0.00040772 </v>
   <v>       0.00006017       0.00000822      -0.00037612 </v>
   <v>       0.00003726      -0.00000087      -0.00021332 </v>
   <v>      -0.00008228      -0.00001205      -0.00038479 </v>
   <v>      -0.00011473      -0.00007839      -0.00041711 </v>
   <v>       0.00008935       0.00001709      -0.00035151 </v>
   <v>       0.00001309       0.00004069      -0.00056538 </v>
   <v>      -0.00005797      -0.00000124      -0.00048604 </v>
   <v>       0.00001017      -0.00003972      -0.00042056 </v>
   <v>      -0.00000762      -0.00000012      -0.00048867 </v>
   <v>       0.00006855      -0.00002038      -0.00046435 </v>
   <v>       0.00008868       0.00001370      -0.00098143 </v>
   <v>       0.00000328       0.00002007      -0.00054933 </v>
   <v>      -0.00015893      -0.00003545      -0.00063081 </v>
   <v>       0.00002914       0.00000760      -0.00058542 </v>
   <v>      -0.00009418       0.00012248      -0.00050364 </v>
   <v>       0.00011098       0.00001005      -0.00058672 </v>
   <v>      -0.00009629      -0.00010253      -0.00066395 </v>
   <v>       0.00004302       0.00001036      -0.00072160 </v>
   <v>      -0.00018164       0.00002465      -0.00055939 </v>
   <v>      -0.00002249      -0.00002733      -0.00063766 </v>
   <v>       0.00006825      -0.00002387      -0.00020190 </v>
   <v>       0.01173925       0.00896133      -0.02367313 </v>
   <v>       0.00010939       0.00035017      -0.00072562 </v>
   <v>       0.00089821      -0.00014408      -0.00036060 </v>
   <v>      -0.00004312       0.00025317      -0.00073596 </v>
   <v>       0.00032651       0.00041494      -0.00115079 </v>
   <v>      -0.00354803       0.00010078      -0.00063154 </v>
   <v>       0.00032641      -0.00046873      -0.00041900 </v>
   <v>      -0.00048966      -0.00003113      -0.00078575 </v>
   <v>       0.00085044       0.00017875      -0.00119984 </v>
   <v>       0.00004656      -0.00031826      -0.00083304 </v>
   <v>       0.01141301      -0.00851052       0.02104409 </v>
   <v>      -0.00010790      -0.00022512      -0.00082656 </v>
   <v>      -0.00004874       0.00000497      -0.00071344 </v>
   <v>       0.00001184      -0.00015892      -0.00062785 </v>
   <v>      -0.00026718      -0.00000836      -0.00070537 </v>
   <v>       0.00004134       0.00018041      -0.00079197 </v>
   <v>      -0.11246941      -0.00047454      -0.00036275 </v>
   <v>       0.00029154       0.00051224      -0.00085077 </v>
   <v>       0.00119601       0.00000198      -0.00088262 </v>
   <v>       0.00029784      -0.00052776      -0.00091477 </v>
   <v>       0.00121043      -0.00034041      -0.00044495 </v>
   <v>       0.00131859      -0.00072481      -0.00131487 </v>
   <v>       0.00571351       0.01497418      -0.00044544 </v>
   <v>       0.00589624       0.01228029      -0.00311533 </v>
   <v>       0.00062288       0.00002032      -0.00092810 </v>
   <v>       0.03123271      -0.00129755       0.00194062 </v>
   <v>       0.00006250       0.00003415      -0.00092281 </v>
   <v>       0.02773306       0.00123223      -0.00349626 </v>
   <v>       0.00120731       0.00033625      -0.00144912 </v>
   <v>       0.00607583      -0.01306976       0.00133801 </v>
   <v>       0.00556227      -0.01422683      -0.00141867 </v>
   <v>       0.00125273       0.00068755      -0.00053790 </v>
   <v>       0.00166541       0.00177435       0.00367771 </v>
   <v>      -0.00140226       0.00004235      -0.00076824 </v>
   <v>       0.00173050      -0.00180302      -0.00512395 </v>
   <v>      -0.00028079      -0.00000043      -0.00075582 </v>
