  <varray name="forces" >
   <v>       0.00066922       0.00116134       0.16295661 </v>
   <v>       0.00086005       0.00011523       0.16243018 </v>
   <v>       0.00266162      -0.00001911       0.16243677 </v>
   <v>       0.00069674      -0.00112318       0.16185107 </v>
   <v>       0.00047110       0.00001523       0.16239013 </v>
   <v>      -0.00019048       0.00039112       0.16051566 </v>
   <v>       0.00067426       0.00001112       0.16239584 </v>
   <v>       0.00086360      -0.00010140       0.16235942 </v>
   <v>      -0.00025068      -0.00040715       0.16428635 </v>
   <v>       0.00096654       0.00132212      -0.11051952 </v>
   <v>      -0.00101359       0.00001823      -0.10616639 </v>
   <v>      -0.00096627      -0.00000767      -0.10607526 </v>
   <v>       0.00094125      -0.00125728      -0.10163188 </v>
   <v>      -0.00127902      -0.00000302      -0.10604910 </v>
   <v>      -0.00090526       0.00044203      -0.10527705 </v>
   <v>      -0.00166829       0.00000739      -0.10606203 </v>
   <v>      -0.00101710      -0.00003835      -0.10598504 </v>
   <v>      -0.00087927      -0.00045420      -0.10684969 </v>
   <v>      -0.10971451      -0.05458536      -0.09388850 </v>
   <v>       0.00272676       0.00033444      -0.05406535 </v>
   <v>       0.00333916       0.00001188      -0.05390833 </v>
   <v>      -0.10351739       0.04968793      -0.01739169 </v>
   <v>      -0.01636974      -0.00069425      -0.05384893 </v>
   <v>      -0.00138244      -0.00112185      -0.05166698 </v>
   <v>       0.00051849      -0.00006445      -0.05390367 </v>
   <v>       0.00268862      -0.00039516      -0.05373394 </v>
   <v>      -0.00149665       0.00113899      -0.05616029 </v>
   <v>       0.26073611       0.00551030      -0.00023284 </v>
   <v>       0.00062748       0.00762895      -0.00841070 </v>
   <v>       0.00063049       0.00479860      -0.00724231 </v>
   <v>      -0.00996473       0.00147460      -0.00300009 </v>
   <v>       0.00072286      -0.00759451       0.00014773 </v>
   <v>      -0.00296686       0.00002825      -0.00417759 </v>
   <v>      -0.01016488      -0.00134750      -0.00531997 </v>
   <v>      -0.00296737       0.00002312      -0.00415912 </v>
   <v>       0.00071629      -0.00477923      -0.00100521 </v>
   <v>      -0.01560026      -0.00019209       0.00363473 </v>
   <v>       0.00110072      -0.00081358       0.00371674 </v>
   <v>       0.00113061      -0.00067369       0.00329248 </v>
   <v>       0.00236927      -0.00013129       0.00387859 </v>
   <v>       0.00105763       0.00079907       0.00489592 </v>
   <v>       0.00080969      -0.00000234       0.00431551 </v>
   <v>       0.00241010       0.00005817       0.00472694 </v>
   <v>       0.00162179      -0.00000457       0.00430227 </v>
   <v>       0.00110573       0.00069516       0.00531944 </v>
   <v>      -0.00040453      -0.00064744       0.00583416 </v>
   <v>      -0.00115431       0.00039860      -0.00252479 </v>
   <v>      -0.00158011       0.00000812      -0.00312048 </v>
   <v>      -0.00034305       0.00074545      -0.01210780 </v>
   <v>      -0.00072050       0.00000986      -0.00312587 </v>
   <v>      -0.00084485       0.00007012      -0.00317308 </v>
   <v>      -0.00183478       0.00002808      -0.00312325 </v>
   <v>      -0.00112754      -0.00040242      -0.00372510 </v>
   <v>      -0.00085730      -0.00008074      -0.00308167 </v>
   <v>      -0.00022986       0.00005256       0.00046319 </v>
   <v>      -0.00052495       0.00010184       0.00201043 </v>
   <v>      -0.00033399      -0.00001265       0.00027389 </v>
   <v>      -0.00022369      -0.00007583       0.00007465 </v>
   <v>      -0.00033792      -0.00000702       0.00026921 </v>
   <v>      -0.00015612       0.00004781       0.00020750 </v>
   <v>      -0.00025800      -0.00001460       0.00027782 </v>
   <v>      -0.00050783      -0.00010873      -0.00148962 </v>
   <v>      -0.00016467      -0.00006489       0.00035009 </v>
   <v>       0.00004271       0.00000905      -0.00325538 </v>
   <v>      -0.00002421       0.00000206      -0.00326848 </v>
   <v>       0.00003099       0.00001836      -0.00333992 </v>
   <v>       0.00000185      -0.00004677      -0.00332947 </v>
   <v>      -0.00002546       0.00001749      -0.00324593 </v>
   <v>      -0.00003157       0.00000967      -0.00325342 </v>
   <v>       0.00000273       0.00006566      -0.00318301 </v>
   <v>      -0.00002438       0.00001115      -0.00326154 </v>
   <v>       0.00003049       0.00000143      -0.00317102 </v>
   <v>       0.00012025       0.00000250      -0.00043295 </v>
   <v>       0.00012352      -0.00001026      -0.00058286 </v>
   <v>       0.00012267       0.00000090      -0.00044798 </v>
   <v>       0.00012004      -0.00000030      -0.00046384 </v>
   <v>       0.00010777       0.00000125      -0.00044896 </v>
   <v>       0.00011898      -0.00000557      -0.00049615 </v>
   <v>       0.00014325       0.00000158      -0.00044850 </v>
   <v>       0.00012371       0.00001227      -0.00031590 </v>
   <v>       0.00011901       0.00000752      -0.00039998 </v>
   <v>       0.00006704      -0.00001456       0.00078472 </v>
   <v>       0.00007844      -0.00002074       0.00076952 </v>
   <v>       0.00006455      -0.00001286       0.00078133 </v>
   <v>       0.00006723      -0.00001137       0.00077888 </v>
   <v>       0.00006988      -0.00001255       0.00078162 </v>
   <v>       0.00007901      -0.00001550       0.00073807 </v>
   <v>       0.00008379      -0.00001298       0.00078188 </v>
   <v>       0.00007849      -0.00000467       0.00079343 </v>
   <v>       0.00007881      -0.00000986       0.00082465 </v>
   <v>      -0.00170218       0.00128932      -0.00386506 </v>
   <v>       0.00041458      -0.00059633      -0.00213571 </v>
   <v>       0.00051186       0.00001234      -0.00196405 </v>
   <v>      -0.00173614      -0.00128683      -0.00001240 </v>
   <v>      -0.00001117       0.00000574      -0.00197197 </v>
   <v>       0.00035368      -0.00020025      -0.00196280 </v>
   <v>       0.00146533       0.00000511      -0.00196483 </v>
   <v>       0.00041469       0.00061692      -0.00180386 </v>
   <v>       0.00036245       0.00022615      -0.00197751 </v>
   <v>       0.00003667      -0.00016506       0.00399725 </v>
   <v>      -0.00017811       0.00009898       0.00342174 </v>
   <v>       0.00001189      -0.00001063       0.00411639 </v>
   <v>       0.00003538       0.00014963       0.00423421 </v>
   <v>       0.00030855      -0.00001084       0.00411764 </v>
   <v>       0.00012347      -0.00006069       0.00406077 </v>
   <v>       0.00021333      -0.00000833       0.00411306 </v>
   <v>      -0.00018182      -0.00012259       0.00482710 </v>
   <v>       0.00012510       0.00004214       0.00416410 </v>
   <v>      -0.00012250      -0.00000084       0.00159894 </v>
   <v>      -0.00000389      -0.00001858       0.00155695 </v>
   <v>      -0.00012572       0.00005554       0.00162439 </v>
   <v>      -0.00009851       0.00006834       0.00166833 </v>
   <v>      -0.00000382       0.00001540       0.00164400 </v>
   <v>      -0.00004957      -0.00000070       0.00159902 </v>
   <v>      -0.00009798      -0.00006999       0.00153151 </v>
   <v>      -0.00034728      -0.00000234       0.00160295 </v>
   <v>      -0.00012559      -0.00005581       0.00157441 </v>
   <v>      -0.00008509       0.00001209      -0.00075932 </v>
   <v>      -0.00012210       0.00000787      -0.00069589 </v>
   <v>      -0.00008641       0.00001331      -0.00075146 </v>
   <v>      -0.00008532       0.00001347      -0.00074285 </v>
   <v>      -0.00005183       0.00001237      -0.00075080 </v>
   <v>      -0.00009212       0.00003643      -0.00072515 </v>
   <v>      -0.00011396       0.00001270      -0.00075093 </v>
   <v>      -0.00012198       0.00001723      -0.00080520 </v>
   <v>      -0.00009206      -0.00001005      -0.00077768 </v>
   <v>       0.00000344       0.00000001       0.00018171 </v>
   <v>      -0.00000501       0.00000786       0.00017821 </v>
   <v>       0.00000913      -0.00000038       0.00018049 </v>
   <v>       0.00000342      -0.00000042       0.00017931 </v>
   <v>       0.00000305      -0.00000033       0.00018047 </v>
   <v>      -0.00000947      -0.00000140       0.00017410 </v>
   <v>      -0.00000775      -0.00000025       0.00018050 </v>
   <v>      -0.00000501      -0.00000847       0.00018272 </v>
   <v>      -0.00000940       0.00000055       0.00018689 </v>
   <v>      -0.00015199      -0.00057424       0.00013586 </v>
   <v>      -0.00022025      -0.00007593       0.00002258 </v>
   <v>      -0.00114344       0.00001087       0.00003122 </v>
   <v>      -0.00015603       0.00056798      -0.00007763 </v>
   <v>       0.00020530       0.00000380       0.00002569 </v>
   <v>       0.00103918      -0.00047902      -0.00054301 </v>
   <v>      -0.00008851       0.00000165       0.00002705 </v>
   <v>      -0.00022036       0.00007629       0.00003112 </v>
   <v>       0.00104493       0.00048715       0.00058840 </v>
