  <varray name="forces" >
   <v>      -0.00041712       0.00022402       0.19983589 </v>
   <v>       0.00060962       0.00038467       0.19962956 </v>
   <v>       0.00025387      -0.00028831       0.19995181 </v>
   <v>       0.00022495      -0.00018124       0.19983954 </v>
   <v>      -0.00066161       0.00116397       0.20029287 </v>
   <v>       0.00067599      -0.00079548       0.19872016 </v>
   <v>       0.00015535      -0.00039322       0.19989100 </v>
   <v>       0.00003287       0.00019207       0.19982237 </v>
   <v>      -0.00094365      -0.00018388       0.20064588 </v>
   <v>       0.00098480       0.00059398      -0.15055945 </v>
   <v>      -0.00017253       0.00013829      -0.14991139 </v>
   <v>       0.00001933      -0.00031678      -0.14981482 </v>
   <v>       0.00048639      -0.00008620      -0.14999695 </v>
   <v>       0.00014645      -0.00103770      -0.15043158 </v>
   <v>      -0.00015902       0.00134967      -0.14904407 </v>
   <v>      -0.00146361      -0.00050067      -0.14951422 </v>
   <v>       0.00006191       0.00005443      -0.14992753 </v>
   <v>       0.00012997      -0.00032578      -0.14986756 </v>
   <v>      -0.00463347      -0.00230422      -0.05947537 </v>
   <v>       0.00060554      -0.00033872      -0.05742038 </v>
   <v>       0.00010136       0.00035813      -0.05792049 </v>
   <v>       0.00301731      -0.00214949      -0.06199436 </v>
   <v>      -0.00067273       0.00500902      -0.05970248 </v>
   <v>       0.00083762      -0.00107359      -0.06263546 </v>
   <v>       0.00164378      -0.00040757      -0.06055385 </v>
   <v>       0.00004334      -0.00008294      -0.05776324 </v>
   <v>      -0.00093628       0.00088761      -0.05855926 </v>
   <v>       0.00787130      -0.00432143      -0.16026494 </v>
   <v>      -0.00099690       0.01043938       0.00568866 </v>
   <v>       0.00111436      -0.00148485       0.00755751 </v>
   <v>       0.00023382       0.00060689       0.00673398 </v>
   <v>       0.00109432      -0.00031207       0.00773648 </v>
   <v>      -0.00216719      -0.00072138       0.00660746 </v>
   <v>      -0.00808928      -0.00321446       0.00516932 </v>
   <v>      -0.00003173       0.00018941       0.00683570 </v>
   <v>       0.00100493      -0.00109367       0.00804796 </v>
   <v>       0.04186794      -0.02523896       0.23944117 </v>
   <v>      -0.00438141       0.04689756      -0.03435502 </v>
   <v>      -0.00232863      -0.00045184      -0.00113219 </v>
   <v>       0.00122151       0.00102523       0.00191381 </v>
   <v>       0.00449851      -0.00079106       0.00328986 </v>
   <v>      -0.00076804       0.00275072      -0.00309086 </v>
   <v>      -0.04392874      -0.02147892      -0.03170420 </v>
   <v>      -0.00031081       0.00015210       0.00096617 </v>
   <v>       0.00286524      -0.00242800       0.00287947 </v>
   <v>       0.03876181      -0.01389917       0.07045093 </v>
   <v>      -0.00033173      -0.00171452       0.00009953 </v>
   <v>       0.00303045       0.03851233      -0.03162977 </v>
   <v>      -0.03942710      -0.01773524      -0.03142351 </v>
   <v>       0.00265526      -0.00343814       0.00069052 </v>
   <v>      -0.00093162      -0.00066821      -0.00070517 </v>
   <v>       0.00166170       0.00228482       0.00003320 </v>
   <v>      -0.00209970       0.00160816      -0.00131920 </v>
   <v>      -0.00199493      -0.00542998       0.00036934 </v>
   <v>       0.00692184       0.03284566       0.06650854 </v>
   <v>       0.00062962       0.00019868       0.00899151 </v>
   <v>       0.03526663      -0.00906648      -0.01671342 </v>
   <v>      -0.00834053      -0.00756129       0.00669064 </v>
   <v>      -0.00091419       0.00016699       0.00987331 </v>
   <v>      -0.00054109       0.00305195       0.01235365 </v>
   <v>       0.00068088      -0.00393500       0.00779959 </v>
   <v>      -0.00008765       0.00058013       0.00802780 </v>
   <v>      -0.03712390      -0.01763571      -0.01624396 </v>
   <v>       0.08873059       0.05590423       0.15413932 </v>
   <v>       0.00501402      -0.00281257      -0.00051373 </v>
   <v>       0.00005110      -0.00081810       0.00402044 </v>
   <v>       0.10013641      -0.05409551      -0.03685926 </v>
   <v>      -0.00094390      -0.00305324      -0.00018861 </v>
   <v>       0.00069063       0.00113191       0.00391336 </v>
   <v>      -0.00337170       0.00050085       0.00421574 </v>
   <v>      -0.00205611      -0.00117252       0.00446564 </v>
   <v>      -0.00043055      -0.00288265       0.00421247 </v>
   <v>       0.00449507      -0.00355387      -0.00548882 </v>
   <v>       0.00017459      -0.00015098       0.00042232 </v>
   <v>      -0.00012943       0.00099868       0.00023246 </v>
   <v>      -0.00099526      -0.00015489      -0.00071513 </v>
   <v>      -0.00091999      -0.00093019      -0.00105742 </v>
   <v>      -0.00008221       0.00002456       0.00018338 </v>
   <v>       0.00566866      -0.00330457      -0.00431679 </v>
   <v>       0.00074340      -0.00063365      -0.00082303 </v>
   <v>       0.00003473       0.00765248      -0.00483703 </v>
   <v>       0.00186567      -0.00118805      -0.00125265 </v>
   <v>      -0.00000398       0.00021187      -0.00035864 </v>
   <v>      -0.00022008       0.00014449      -0.00043916 </v>
   <v>       0.00081261       0.00061212       0.00032446 </v>
   <v>       0.00007258      -0.00019444      -0.00029441 </v>
   <v>      -0.00008503       0.00012506      -0.00032875 </v>
   <v>       0.00045583      -0.00033120      -0.00045621 </v>
   <v>       0.00024701       0.00059722      -0.00069658 </v>
   <v>       0.00022775       0.00012501      -0.00035012 </v>
   <v>      -0.00115532       0.03721338       0.04666444 </v>
   <v>       0.03394996      -0.01718746      -0.02981771 </v>
   <v>      -0.00011472      -0.00107891      -0.01082784 </v>
   <v>      -0.00063551      -0.00049474      -0.02128450 </v>
   <v>      -0.03255414      -0.01740565      -0.02811933 </v>
   <v>       0.00004052      -0.00012099      -0.01134264 </v>
   <v>       0.00007391      -0.00213685      -0.00966330 </v>
   <v>       0.00051807       0.00284210      -0.01202454 </v>
   <v>       0.00025200      -0.00027187      -0.00655001 </v>
   <v>      -0.26298127      -0.02220000      -0.02960428 </v>
   <v>      -0.00116717      -0.00395136      -0.00164183 </v>
   <v>      -0.00135979      -0.00797015      -0.00029187 </v>
   <v>       0.01057183      -0.00065524      -0.00326310 </v>
   <v>      -0.00044434       0.00753385      -0.00877635 </v>
   <v>       0.00228817       0.00050453      -0.00462700 </v>
   <v>       0.05879753      -0.03145810      -0.03613265 </v>
   <v>       0.00118772       0.00244908      -0.00683283 </v>
   <v>      -0.00134181       0.06310795      -0.04025770 </v>
   <v>      -0.00253777       0.00299646      -0.00301585 </v>
   <v>       0.00059790      -0.00022355       0.00084168 </v>
   <v>       0.00222397      -0.00059205       0.00165312 </v>
   <v>       0.00013922      -0.00095735       0.00562321 </v>
   <v>      -0.00033525       0.00057808       0.00133190 </v>
   <v>       0.00037758      -0.00045827       0.00146398 </v>
   <v>      -0.00102870       0.00081213       0.00070881 </v>
   <v>      -0.00010591      -0.00169204       0.00046593 </v>
   <v>      -0.00094229      -0.00040008       0.00144874 </v>
   <v>      -0.00011421      -0.00079743       0.00132776 </v>
   <v>      -0.00089936       0.00056100       0.00038863 </v>
   <v>       0.00006097       0.00022979       0.00109347 </v>
   <v>       0.00019618       0.00037244       0.00115334 </v>
   <v>       0.00105371       0.00029118       0.00125069 </v>
   <v>       0.00022608       0.00023195       0.00100364 </v>
   <v>      -0.00022041      -0.00048157       0.00115165 </v>
   <v>      -0.00115426      -0.00069435       0.00113589 </v>
   <v>      -0.00057991       0.00018091       0.00115336 </v>
   <v>      -0.00000119       0.00020786       0.00001187 </v>
   <v>       0.00036967      -0.00026670      -0.00029229 </v>
   <v>      -0.00012521      -0.00007547      -0.00002204 </v>
   <v>      -0.00009121      -0.00011142       0.00011599 </v>
   <v>      -0.00032261      -0.00007514       0.00007773 </v>
   <v>      -0.00008134      -0.00005909       0.00004065 </v>
   <v>       0.00001766       0.00012433       0.00004532 </v>
   <v>       0.00042166       0.00033437       0.00008572 </v>
   <v>       0.00016881      -0.00008893      -0.00000066 </v>
   <v>       0.00017207      -0.00009375      -0.00028930 </v>
   <v>      -0.00021768      -0.00018974      -0.00036832 </v>
   <v>      -0.00010078       0.00019096      -0.00027159 </v>
   <v>      -0.00014521       0.00003798      -0.00027984 </v>
   <v>       0.00025355      -0.00073379      -0.00023679 </v>
   <v>      -0.00046932       0.00048501      -0.00042949 </v>
   <v>      -0.00001253       0.00011090      -0.00032110 </v>
   <v>      -0.00003324      -0.00005886      -0.00033208 </v>
   <v>       0.00057593       0.00025295      -0.00018448 </v>
