  <varray name="forces" >
   <v>       0.00013805      -0.00023604      -0.19098256 </v>
   <v>       0.00062330      -0.00021089      -0.18747476 </v>
   <v>      -0.00013248       0.00049019      -0.18732907 </v>
   <v>      -0.00062553      -0.00005495      -0.18739899 </v>
   <v>       0.00009493      -0.00016757       0.00427883 </v>
   <v>      -0.00774684       0.00459078       0.00313601 </v>
   <v>      -0.00009764      -0.00920773       0.00026607 </v>
   <v>       0.00778540       0.00472656       0.00168825 </v>
   <v>       0.00358779      -0.00611658      -0.00041574 </v>
   <v>       0.00681597      -0.00013528      -0.00038408 </v>
   <v>      -0.00336404       0.00222800      -0.00672915 </v>
   <v>      -0.00686101       0.00372935      -0.00356012 </v>
   <v>       0.00675893      -0.01165774       0.14642761 </v>
   <v>       0.01240071       0.00008583       0.15014400 </v>
   <v>      -0.00628612       0.00539749      -0.13945827 </v>
   <v>      -0.01282386       0.00710351       0.00962882 </v>
   <v>       0.02896399       0.00294003       0.00257025 </v>
   <v>      -0.01687091       0.00695895      -0.00617206 </v>
   <v>      -0.03020843       0.02170646      -0.00171391 </v>
   <v>      -0.00000517       0.00000893      -0.04619653 </v>
   <v>       0.00079357       0.00044120      -0.05386964 </v>
   <v>       0.00001030      -0.00090484      -0.05391113 </v>
   <v>      -0.00079292       0.00044684      -0.05381484 </v>
   <v>       0.00029454      -0.00050225      -0.01478554 </v>
   <v>       0.04278029       0.02538189       0.02409425 </v>
   <v>      -0.00029669      -0.04996741       0.02694320 </v>
   <v>      -0.04273381       0.02500779       0.02116583 </v>
   <v>       0.02715696      -0.04681796      -0.00321425 </v>
   <v>      -0.05954163       0.03614710      -0.02042370 </v>
   <v>      -0.03069766       0.01620359      -0.03944606 </v>
   <v>       0.05929097       0.00084139      -0.00156648 </v>
   <v>       0.00034069      -0.00067045      -0.08077608 </v>
   <v>       0.00120906      -0.00419562      -0.00346819 </v>
   <v>       0.00213098      -0.02082749       0.08118949 </v>
   <v>       0.01790718      -0.01277245      -0.08052004 </v>
   <v>      -0.00000636       0.00051391       0.22371450 </v>
   <v>       0.00046284      -0.00024982       0.22338004 </v>
   <v>      -0.00046545      -0.00023823       0.22355109 </v>
   <v>       0.00001035      -0.00002069       0.22280925 </v>
   <v>      -0.00000086       0.00000224      -0.00032914 </v>
   <v>      -0.00034071       0.00019812      -0.00036516 </v>
   <v>       0.00034097       0.00019818      -0.00034878 </v>
   <v>       0.00000034      -0.00039435      -0.00033322 </v>
